{
  "optimization_type": "component",
  "targets": [
    "ma_crossover"
  ],
  "method": "grid_search",
  "components_optimized": 1,
  "results": {
    "strategy_ma_crossover": {
      "method": "grid_search",
      "component": "strategy_ma_crossover",
      "parameter_space": "strategy_ma_crossover_params",
      "combinations_tested": 9,
      "best_parameters": {
        "generate_exit_signals": true,
        "min_separation": 0.0001,
        "fast_ma.lookback_period": 10,
        "slow_ma.lookback_period": 30
      },
      "best_score": 0.1903459293363885,
      "test_score": null,
      "all_results": [
        {
          "parameters": {
            "generate_exit_signals": true,
            "min_separation": 0.0001,
            "fast_ma.lookback_period": 5,
            "slow_ma.lookback_period": 20
          },
          "score": -5.707609694131856,
          "regime_performance": {
            "default": {
              "total_return": -600.4500000000348,
              "sharpe_ratio": -3.3028920673176634,
              "win_rate": 0.2716049382716049,
              "trade_count": 81,
              "avg_win": 0,
              "avg_loss": 7.412962962963393,
              "parameters": {
                "generate_exit_signals": true,
                "min_separation": 0.0001,
                "fast_ma.lookback_period": 5,
                "slow_ma.lookback_period": 20
              }
            },
            "trending_up": {
              "total_return": 203.09999999998354,
              "sharpe_ratio": 2.4124904045292057,
              "win_rate": 0.3023255813953488,
              "trade_count": 86,
              "avg_win": 2.361627906976553,
              "avg_loss": 0,
              "parameters": {
                "generate_exit_signals": true,
                "min_separation": 0.0001,
                "fast_ma.lookback_period": 5,
                "slow_ma.lookback_period": 20
              }
            },
            "trending_down": {
              "total_return": 194.6100000000115,
              "sharpe_ratio": 2.993840632875735,
              "win_rate": 0.3076923076923077,
              "trade_count": 39,
              "avg_win": 4.990000000000295,
              "avg_loss": 0,
              "parameters": {
                "generate_exit_signals": true,
                "min_separation": 0.0001,
                "fast_ma.lookback_period": 5,
                "slow_ma.lookback_period": 20
              }
            }
          }
        },
        {
          "parameters": {
            "generate_exit_signals": true,
            "min_separation": 0.0001,
            "fast_ma.lookback_period": 5,
            "slow_ma.lookback_period": 30
          },
          "score": -0.9574664050709413,
          "regime_performance": {
            "trending_down": {
              "total_return": 296.87000000000126,
              "sharpe_ratio": 5.083735992419434,
              "win_rate": 0.3235294117647059,
              "trade_count": 34,
              "avg_win": 8.73147058823533,
              "avg_loss": 0,
              "parameters": {
                "generate_exit_signals": true,
                "min_separation": 0.0001,
                "fast_ma.lookback_period": 5,
                "slow_ma.lookback_period": 30
              }
            },
            "default": {
              "total_return": -644.1499999999678,
              "sharpe_ratio": -3.752642500697754,
              "win_rate": 0.2916666666666667,
              "trade_count": 72,
              "avg_win": 0,
              "avg_loss": 8.94652777777733,
              "parameters": {
                "generate_exit_signals": true,
                "min_separation": 0.0001,
                "fast_ma.lookback_period": 5,
                "slow_ma.lookback_period": 30
              }
            },
            "trending_up": {
              "total_return": 312.9999999999882,
              "sharpe_ratio": 4.64360381644073,
              "win_rate": 0.3561643835616438,
              "trade_count": 73,
              "avg_win": 4.2876712328765505,
              "avg_loss": 0,
              "parameters": {
                "generate_exit_signals": true,
                "min_separation": 0.0001,
                "fast_ma.lookback_period": 5,
                "slow_ma.lookback_period": 30
              }
            }
          }
        },
        {
          "parameters": {
            "generate_exit_signals": true,
            "min_separation": 0.0001,
            "fast_ma.lookback_period": 5,
            "slow_ma.lookback_period": 40
          },
          "score": -0.0598359288441092,
          "regime_performance": {
            "trending_down": {
              "total_return": 274.8700000000099,
              "sharpe_ratio": 4.725261425858512,
              "win_rate": 0.27586206896551724,
              "trade_count": 29,
              "avg_win": 9.478275862069307,
              "avg_loss": 0,
              "parameters": {
                "generate_exit_signals": true,
                "min_separation": 0.0001,
                "fast_ma.lookback_period": 5,
                "slow_ma.lookback_period": 40
              }
            },
            "default": {
              "total_return": -621.0700000000202,
              "sharpe_ratio": -3.6893388312170923,
              "win_rate": 0.2857142857142857,
              "trade_count": 70,
              "avg_win": 0,
              "avg_loss": 8.872428571428859,
              "parameters": {
                "generate_exit_signals": true,
                "min_separation": 0.0001,
                "fast_ma.lookback_period": 5,
                "slow_ma.lookback_period": 40
              }
            },
            "trending_up": {
              "total_return": 343.49999999999454,
              "sharpe_ratio": 5.3674437977784075,
              "win_rate": 0.38333333333333336,
              "trade_count": 60,
              "avg_win": 5.724999999999909,
              "avg_loss": 0,
              "parameters": {
                "generate_exit_signals": true,
                "min_separation": 0.0001,
                "fast_ma.lookback_period": 5,
                "slow_ma.lookback_period": 40
              }
            }
          }
        },
        {
          "parameters": {
            "generate_exit_signals": true,
            "min_separation": 0.0001,
            "fast_ma.lookback_period": 10,
            "slow_ma.lookback_period": 20
          },
          "score": -5.173648695123943,
          "regime_performance": {
            "trending_down": {
              "total_return": 198.63000000000284,
              "sharpe_ratio": 3.432539914649395,
              "win_rate": 0.38461538461538464,
              "trade_count": 39,
              "avg_win": 5.093076923076996,
              "avg_loss": 0,
              "parameters": {
                "generate_exit_signals": true,
                "min_separation": 0.0001,
                "fast_ma.lookback_period": 10,
                "slow_ma.lookback_period": 20
              }
            },
            "default": {
              "total_return": -620.4199999999673,
              "sharpe_ratio": -3.741982240040322,
              "win_rate": 0.3076923076923077,
              "trade_count": 65,
              "avg_win": 0,
              "avg_loss": 9.544923076922574,
              "parameters": {
                "generate_exit_signals": true,
                "min_separation": 0.0001,
                "fast_ma.lookback_period": 10,
                "slow_ma.lookback_period": 20
              }
            },
            "trending_up": {
              "total_return": 239.00999999999613,
              "sharpe_ratio": 3.5766419029542886,
              "win_rate": 0.3291139240506329,
              "trade_count": 79,
              "avg_win": 3.0254430379746347,
              "avg_loss": 0,
              "parameters": {
                "generate_exit_signals": true,
                "min_separation": 0.0001,
                "fast_ma.lookback_period": 10,
                "slow_ma.lookback_period": 20
              }
            }
          }
        },
        {
          "parameters": {
            "generate_exit_signals": true,
            "min_separation": 0.0001,
            "fast_ma.lookback_period": 10,
            "slow_ma.lookback_period": 30
          },
          "score": 0.1903459293363885,
          "regime_performance": {
            "trending_down": {
              "total_return": 278.85999999998603,
              "sharpe_ratio": 5.338650034299393,
              "win_rate": 0.35135135135135137,
              "trade_count": 37,
              "avg_win": 7.536756756756379,
              "avg_loss": 0,
              "parameters": {
                "generate_exit_signals": true,
                "min_separation": 0.0001,
                "fast_ma.lookback_period": 10,
                "slow_ma.lookback_period": 30
              }
            },
            "default": {
              "total_return": -612.7299999999536,
              "sharpe_ratio": -3.5801953464197904,
              "win_rate": 0.30434782608695654,
              "trade_count": 69,
              "avg_win": 0,
              "avg_loss": 8.880144927535559,
              "parameters": {
                "generate_exit_signals": true,
                "min_separation": 0.0001,
                "fast_ma.lookback_period": 10,
                "slow_ma.lookback_period": 30
              }
            },
            "trending_up": {
              "total_return": 339.94999999997617,
              "sharpe_ratio": 5.641170955524447,
              "win_rate": 0.33766233766233766,
              "trade_count": 77,
              "avg_win": 4.414935064934755,
              "avg_loss": 0,
              "parameters": {
                "generate_exit_signals": true,
                "min_separation": 0.0001,
                "fast_ma.lookback_period": 10,
                "slow_ma.lookback_period": 30
              }
            }
          }
        },
        {
          "parameters": {
            "generate_exit_signals": true,
            "min_separation": 0.0001,
            "fast_ma.lookback_period": 10,
            "slow_ma.lookback_period": 40
          },
          "score": -2.190197420123666,
          "regime_performance": {
            "default": {
              "total_return": -693.3599999999046,
              "sharpe_ratio": -4.055789070716366,
              "win_rate": 0.2898550724637681,
              "trade_count": 69,
              "avg_win": 0,
              "avg_loss": 10.048695652172531,
              "parameters": {
                "generate_exit_signals": true,
                "min_separation": 0.0001,
                "fast_ma.lookback_period": 10,
                "slow_ma.lookback_period": 40
              }
            },
            "trending_down": {
              "total_return": 256.3599999999951,
              "sharpe_ratio": 5.5938563132875725,
              "win_rate": 0.3225806451612903,
              "trade_count": 31,
              "avg_win": 8.269677419354682,
              "avg_loss": 0,
              "parameters": {
                "generate_exit_signals": true,
                "min_separation": 0.0001,
                "fast_ma.lookback_period": 10,
                "slow_ma.lookback_period": 40
              }
            },
            "trending_up": {
              "total_return": 359.9999999999909,
              "sharpe_ratio": 6.583218729859587,
              "win_rate": 0.36923076923076925,
              "trade_count": 65,
              "avg_win": 5.538461538461399,
              "avg_loss": 0,
              "parameters": {
                "generate_exit_signals": true,
                "min_separation": 0.0001,
                "fast_ma.lookback_period": 10,
                "slow_ma.lookback_period": 40
              }
            }
          }
        },
        {
          "parameters": {
            "generate_exit_signals": true,
            "min_separation": 0.0001,
            "fast_ma.lookback_period": 15,
            "slow_ma.lookback_period": 20
          },
          "score": -5.105558462090574,
          "regime_performance": {
            "trending_down": {
              "total_return": 92.08000000000993,
              "sharpe_ratio": 1.3002219054610507,
              "win_rate": 0.36666666666666664,
              "trade_count": 30,
              "avg_win": 3.0693333333336645,
              "avg_loss": 0,
              "parameters": {
                "generate_exit_signals": true,
                "min_separation": 0.0001,
                "fast_ma.lookback_period": 15,
                "slow_ma.lookback_period": 20
              }
            },
            "trending_up": {
              "total_return": 106.4600000000155,
              "sharpe_ratio": 1.6490849493142592,
              "win_rate": 0.38235294117647056,
              "trade_count": 68,
              "avg_win": 1.5655882352943455,
              "avg_loss": 0,
              "parameters": {
                "generate_exit_signals": true,
                "min_separation": 0.0001,
                "fast_ma.lookback_period": 15,
                "slow_ma.lookback_period": 20
              }
            },
            "default": {
              "total_return": -374.36000000001286,
              "sharpe_ratio": -3.3977342661829693,
              "win_rate": 0.3333333333333333,
              "trade_count": 33,
              "avg_win": 0,
              "avg_loss": 11.344242424242815,
              "parameters": {
                "generate_exit_signals": true,
                "min_separation": 0.0001,
                "fast_ma.lookback_period": 15,
                "slow_ma.lookback_period": 20
              }
            }
          }
        },
        {
          "parameters": {
            "generate_exit_signals": true,
            "min_separation": 0.0001,
            "fast_ma.lookback_period": 15,
            "slow_ma.lookback_period": 30
          },
          "score": -5.677037610423956,
          "regime_performance": {
            "trending_down": {
              "total_return": 137.47999999998228,
              "sharpe_ratio": 2.3470634679983515,
              "win_rate": 0.35714285714285715,
              "trade_count": 42,
              "avg_win": 3.2733333333329115,
              "avg_loss": 0,
              "parameters": {
                "generate_exit_signals": true,
                "min_separation": 0.0001,
                "fast_ma.lookback_period": 15,
                "slow_ma.lookback_period": 30
              }
            },
            "default": {
              "total_return": -676.819999999941,
              "sharpe_ratio": -4.197015302302044,
              "win_rate": 0.29310344827586204,
              "trade_count": 58,
              "avg_win": 0,
              "avg_loss": 11.66931034482657,
              "parameters": {
                "generate_exit_signals": true,
                "min_separation": 0.0001,
                "fast_ma.lookback_period": 15,
                "slow_ma.lookback_period": 30
              }
            },
            "trending_up": {
              "total_return": 338.99999999998727,
              "sharpe_ratio": 5.616597501200451,
              "win_rate": 0.3373493975903614,
              "trade_count": 83,
              "avg_win": 4.084337349397437,
              "avg_loss": 0,
              "parameters": {
                "generate_exit_signals": true,
                "min_separation": 0.0001,
                "fast_ma.lookback_period": 15,
                "slow_ma.lookback_period": 30
              }
            }
          }
        },
        {
          "parameters": {
            "generate_exit_signals": true,
            "min_separation": 0.0001,
            "fast_ma.lookback_period": 15,
            "slow_ma.lookback_period": 40
          },
          "score": -8.551021084336913,
          "regime_performance": {
            "default": {
              "total_return": -752.2199999999771,
              "sharpe_ratio": -4.64443958698231,
              "win_rate": 0.25,
              "trade_count": 60,
              "avg_win": 0,
              "avg_loss": 12.536999999999617,
              "parameters": {
                "generate_exit_signals": true,
                "min_separation": 0.0001,
                "fast_ma.lookback_period": 15,
                "slow_ma.lookback_period": 40
              }
            },
            "trending_down": {
              "total_return": 96.85999999996966,
              "sharpe_ratio": 1.911941525662112,
              "win_rate": 0.29411764705882354,
              "trade_count": 34,
              "avg_win": 2.8488235294108724,
              "avg_loss": 0,
              "parameters": {
                "generate_exit_signals": true,
                "min_separation": 0.0001,
                "fast_ma.lookback_period": 15,
                "slow_ma.lookback_period": 40
              }
            },
            "trending_up": {
              "total_return": 355.99999999999454,
              "sharpe_ratio": 5.868543247701004,
              "win_rate": 0.38666666666666666,
              "trade_count": 75,
              "avg_win": 4.746666666666594,
              "avg_loss": 0,
              "parameters": {
                "generate_exit_signals": true,
                "min_separation": 0.0001,
                "fast_ma.lookback_period": 15,
                "slow_ma.lookback_period": 40
              }
            }
          }
        }
      ],
      "regime_best_parameters": {
        "default": {
          "parameters": {
            "generate_exit_signals": true,
            "min_separation": 0.0001,
            "fast_ma.lookback_period": 5,
            "slow_ma.lookback_period": 20
          },
          "sharpe_ratio": -3.3028920673176634,
          "win_rate": 0.2716049382716049,
          "total_return": -600.4500000000348
        },
        "trending_up": {
          "parameters": {
            "generate_exit_signals": true,
            "min_separation": 0.0001,
            "fast_ma.lookback_period": 10,
            "slow_ma.lookback_period": 40
          },
          "sharpe_ratio": 6.583218729859587,
          "win_rate": 0.36923076923076925,
          "total_return": 359.9999999999909
        },
        "trending_down": {
          "parameters": {
            "generate_exit_signals": true,
            "min_separation": 0.0001,
            "fast_ma.lookback_period": 10,
            "slow_ma.lookback_period": 40
          },
          "sharpe_ratio": 5.5938563132875725,
          "win_rate": 0.3225806451612903,
          "total_return": 256.3599999999951
        }
      },
      "regime_statistics": {
        "default": {
          "avg_return": -621.7311111110866,
          "std_return": 98.55848150483739,
          "avg_sharpe": -3.8180032457640345,
          "avg_win_rate": 0.2919242087227539,
          "total_trades": 577,
          "parameter_sets_tested": 9
        },
        "trending_up": {
          "avg_return": 288.891111111103,
          "std_return": 82.57703977961667,
          "avg_sharpe": 4.595421700589153,
          "avg_win_rate": 0.3537999260741738,
          "total_trades": 666,
          "parameter_sets_tested": 9
        },
        "trending_down": {
          "avg_return": 202.95777777777428,
          "std_return": 74.92973920470126,
          "avg_sharpe": 3.6363456902790623,
          "avg_win_rate": 0.3315064822687671,
          "total_trades": 315,
          "parameter_sets_tested": 9
        }
      },
      "timestamp": "2025-05-26T19:35:16.741481"
    }
  },
  "timestamp": "2025-05-26T19:35:16.744932"
}